{
  "user_service": {
    "timestamp": "2025-05-15T06:54:59.505746",
    "status": "healthy",
    "response_time": 0.002105
  },
  "order_service": {
    "timestamp": "2025-05-15T06:54:59.505746",
    "status": "healthy",
    "response_time": 0.001457
  },
  "inventory_service": {
    "timestamp": "2025-05-15T06:54:59.505746",
    "status": "healthy",
    "response_time": 0.001391
  },
  "notification_service": {
    "timestamp": "2025-05-15T06:54:59.505746",
    "status": "healthy",
    "response_time": 0.001342
  }
}