{
  "user_service": {
    "timestamp": "2025-05-09T16:41:47.549450",
    "status": "healthy",
    "response_time": 0.002106
  },
  "order_service": {
    "timestamp": "2025-05-09T16:41:47.549450",
    "status": "healthy",
    "response_time": 0.002007
  },
  "inventory_service": {
    "timestamp": "2025-05-09T16:41:47.549450",
    "status": "healthy",
    "response_time": 0.001648
  },
  "notification_service": {
    "timestamp": "2025-05-09T16:41:47.549450",
    "status": "healthy",
    "response_time": 0.001516
  }
}