{
  "user_service": {
    "timestamp": "2025-05-15T06:53:23.755243",
    "status": "healthy",
    "response_time": 0.001662
  },
  "order_service": {
    "timestamp": "2025-05-15T06:53:23.755243",
    "status": "healthy",
    "response_time": 0.001627
  },
  "inventory_service": {
    "timestamp": "2025-05-15T06:53:23.755243",
    "status": "healthy",
    "response_time": 0.001334
  },
  "notification_service": {
    "timestamp": "2025-05-15T06:53:23.755243",
    "status": "healthy",
    "response_time": 0.001331
  }
}