{
  "user_service": {
    "timestamp": "2025-05-09T14:33:23.448870",
    "status": "healthy",
    "response_time": 0.002448
  },
  "order_service": {
    "timestamp": "2025-05-09T14:33:23.448870",
    "status": "healthy",
    "response_time": 0.002005
  },
  "inventory_service": {
    "timestamp": "2025-05-09T14:33:23.448870",
    "status": "healthy",
    "response_time": 0.001738
  },
  "notification_service": {
    "timestamp": "2025-05-09T14:33:23.448870",
    "status": "healthy",
    "response_time": 0.001642
  }
}