{
  "user_service": {
    "timestamp": "2025-05-14T05:41:33.742064",
    "status": "healthy",
    "response_time": 0.002076
  },
  "order_service": {
    "timestamp": "2025-05-14T05:41:33.742064",
    "status": "healthy",
    "response_time": 0.001856
  },
  "inventory_service": {
    "timestamp": "2025-05-14T05:41:33.742064",
    "status": "healthy",
    "response_time": 0.0016
  },
  "notification_service": {
    "timestamp": "2025-05-14T05:41:33.742064",
    "status": "healthy",
    "response_time": 0.001595
  }
}