{
  "user_service": {
    "timestamp": "2025-05-14T19:14:36.246238",
    "status": "healthy",
    "response_time": 0.001937
  },
  "order_service": {
    "timestamp": "2025-05-14T19:14:36.246238",
    "status": "healthy",
    "response_time": 0.001564
  },
  "inventory_service": {
    "timestamp": "2025-05-14T19:14:36.246238",
    "status": "healthy",
    "response_time": 0.001172
  },
  "notification_service": {
    "timestamp": "2025-05-14T19:14:36.246238",
    "status": "healthy",
    "response_time": 0.001322
  }
}