{
  "user_service": {
    "timestamp": "2025-05-09T14:27:32.410205",
    "status": "healthy",
    "response_time": 0.002212
  },
  "order_service": {
    "timestamp": "2025-05-09T14:27:32.410205",
    "status": "healthy",
    "response_time": 0.002066
  },
  "inventory_service": {
    "timestamp": "2025-05-09T14:27:32.410205",
    "status": "healthy",
    "response_time": 0.001556
  },
  "notification_service": {
    "timestamp": "2025-05-09T14:27:32.410205",
    "status": "healthy",
    "response_time": 0.001611
  }
}