{
  "user_service": {
    "average_response_time": 0.40343256197406663,
    "requests_served": 92,
    "total_users": 3,
    "timestamp": "2025-05-15T07:47:10.359571"
  },
  "order_service": {
    "average_response_time": 0.3689428580929134,
    "requests_served": 45,
    "total_orders": 2,
    "timestamp": "2025-05-15T07:47:10.359571"
  },
  "inventory_service": {
    "average_response_time": 0.257172105667715,
    "requests_served": 29,
    "total_items": 60,
    "unique_items": 3,
    "timestamp": "2025-05-15T07:47:10.359571"
  },
  "notification_service": {
    "average_response_time": 0.164769498516652,
    "requests_served": 35,
    "total_notifications": 0,
    "timestamp": "2025-05-15T07:47:10.359571"
  }
}