{
  "user_service": {
    "average_response_time": 0.44810156255226685,
    "requests_served": 47,
    "total_users": 3,
    "timestamp": "2025-05-09T11:10:36.298404"
  },
  "order_service": {
    "average_response_time": 0.41009539657791183,
    "requests_served": 33,
    "total_orders": 2,
    "timestamp": "2025-05-09T11:10:36.298404"
  },
  "inventory_service": {
    "average_response_time": 0.10301383410802147,
    "requests_served": 47,
    "total_items": 60,
    "unique_items": 3,
    "timestamp": "2025-05-09T11:10:36.298404"
  },
  "notification_service": {
    "average_response_time": 0.16692841184564922,
    "requests_served": 23,
    "total_notifications": 0,
    "timestamp": "2025-05-09T11:10:36.298404"
  }
}