{
  "user_service": {
    "average_response_time": 0.24291166375933604,
    "requests_served": 80,
    "total_users": 3,
    "timestamp": "2025-05-16T23:35:04.436536"
  },
  "order_service": {
    "average_response_time": 0.20724230850594189,
    "cpu_percent": 1.3,
    "memory_mb": 1051.21875,
    "total_orders": 0,
    "timestamp": "2025-05-16T23:35:04.436536"
  },
  "inventory_service": {
    "average_response_time": 0.13417191833900965,
    "requests_served": 62,
    "total_items": 60,
    "unique_items": 3,
    "timestamp": "2025-05-16T23:35:04.436536"
  },
  "notification_service": {
    "average_response_time": 0.07957268140336479,
    "requests_served": 10,
    "total_notifications": 0,
    "timestamp": "2025-05-16T23:35:04.436536"
  }
}