{
  "user_service": {
    "average_response_time": 0.14927061136228015,
    "requests_served": 22,
    "total_users": 3,
    "timestamp": "2025-05-14T15:57:44.334165"
  },
  "order_service": {
    "average_response_time": 0.41276231262770124,
    "requests_served": 46,
    "total_orders": 2,
    "timestamp": "2025-05-14T15:57:44.334165"
  },
  "inventory_service": {
    "average_response_time": 0.09051377321427732,
    "requests_served": 34,
    "total_items": 60,
    "unique_items": 3,
    "timestamp": "2025-05-14T15:57:44.334165"
  },
  "notification_service": {
    "average_response_time": 0.06245856779011366,
    "requests_served": 14,
    "total_notifications": 0,
    "timestamp": "2025-05-14T15:57:44.334165"
  }
}