{
  "user_service": {
    "average_response_time": 0.4451069284035055,
    "requests_served": 12,
    "total_users": 3,
    "timestamp": "2025-05-13T01:55:59.427472"
  },
  "order_service": {
    "average_response_time": 0.4840468624136099,
    "requests_served": 20,
    "total_orders": 2,
    "timestamp": "2025-05-13T01:55:59.427472"
  },
  "inventory_service": {
    "average_response_time": 0.21083745081154331,
    "requests_served": 68,
    "total_items": 60,
    "unique_items": 3,
    "timestamp": "2025-05-13T01:55:59.427472"
  },
  "notification_service": {
    "average_response_time": 0.18704301134503637,
    "requests_served": 20,
    "total_notifications": 0,
    "timestamp": "2025-05-13T01:55:59.427472"
  }
}