{
  "user_service": {
    "average_response_time": 0.2930441155544875,
    "requests_served": 82,
    "total_users": 3,
    "timestamp": "2025-05-17T17:50:26.320610"
  },
  "order_service": {
    "average_response_time": 0.10460532656733104,
    "cpu_percent": 0.0,
    "memory_mb": 1097.0,
    "total_orders": 0,
    "timestamp": "2025-05-17T17:50:26.320610"
  },
  "inventory_service": {
    "average_response_time": 0.29556830991444694,
    "requests_served": 12,
    "total_items": 60,
    "unique_items": 3,
    "timestamp": "2025-05-17T17:50:26.320610"
  },
  "notification_service": {
    "average_response_time": 0.06930555017081871,
    "requests_served": 37,
    "total_notifications": 0,
    "timestamp": "2025-05-17T17:50:26.320610"
  }
}