{
  "user_service": {
    "average_response_time": 0.1344494353691276,
    "requests_served": 80,
    "total_users": 3,
    "timestamp": "2025-05-11T23:16:25.446615"
  },
  "order_service": {
    "average_response_time": 0.47970307230359144,
    "requests_served": 31,
    "total_orders": 2,
    "timestamp": "2025-05-11T23:16:25.446615"
  },
  "inventory_service": {
    "average_response_time": 0.14231156332405714,
    "requests_served": 19,
    "total_items": 60,
    "unique_items": 3,
    "timestamp": "2025-05-11T23:16:25.446615"
  },
  "notification_service": {
    "average_response_time": 0.09087963063665766,
    "requests_served": 21,
    "total_notifications": 0,
    "timestamp": "2025-05-11T23:16:25.446615"
  }
}