{
  "user_service": {
    "average_response_time": 0.16122746178767963,
    "requests_served": 44,
    "total_users": 3,
    "timestamp": "2025-05-12T04:04:56.367143"
  },
  "order_service": {
    "average_response_time": 0.21026277782131658,
    "requests_served": 20,
    "total_orders": 2,
    "timestamp": "2025-05-12T04:04:56.367143"
  },
  "inventory_service": {
    "average_response_time": 0.2975713075937348,
    "requests_served": 75,
    "total_items": 60,
    "unique_items": 3,
    "timestamp": "2025-05-12T04:04:56.367143"
  },
  "notification_service": {
    "average_response_time": 0.14555990884248177,
    "requests_served": 19,
    "total_notifications": 0,
    "timestamp": "2025-05-12T04:04:56.367143"
  }
}