{
  "user_service": {
    "average_response_time": 0.2185590805038435,
    "requests_served": 83,
    "total_users": 3,
    "timestamp": "2025-05-17T15:11:00.900158"
  },
  "order_service": {
    "average_response_time": 0.24654654445163707,
    "cpu_percent": 0.0,
    "memory_mb": 1027.921875,
    "total_orders": 0,
    "timestamp": "2025-05-17T15:11:00.900158"
  },
  "inventory_service": {
    "average_response_time": 0.2471725499477475,
    "requests_served": 18,
    "total_items": 60,
    "unique_items": 3,
    "timestamp": "2025-05-17T15:11:00.900158"
  },
  "notification_service": {
    "average_response_time": 0.09256873468857366,
    "requests_served": 14,
    "total_notifications": 0,
    "timestamp": "2025-05-17T15:11:00.900158"
  }
}