{
  "user_service": {
    "average_response_time": 0.2291941919869395,
    "requests_served": 71,
    "total_users": 3,
    "timestamp": "2025-05-13T00:53:01.188795"
  },
  "order_service": {
    "average_response_time": 0.5734364275047805,
    "requests_served": 7,
    "total_orders": 2,
    "timestamp": "2025-05-13T00:53:01.188795"
  },
  "inventory_service": {
    "average_response_time": 0.2867094690697233,
    "requests_served": 67,
    "total_items": 60,
    "unique_items": 3,
    "timestamp": "2025-05-13T00:53:01.188795"
  },
  "notification_service": {
    "average_response_time": 0.12544156666800765,
    "requests_served": 16,
    "total_notifications": 0,
    "timestamp": "2025-05-13T00:53:01.188795"
  }
}