{
  "user_service": {
    "average_response_time": 0.16896361553030648,
    "requests_served": 47,
    "total_users": 3,
    "timestamp": "2025-05-16T22:18:14.295121"
  },
  "order_service": {
    "average_response_time": 0.11552321140559685,
    "cpu_percent": 0.0,
    "memory_mb": 1057.75,
    "total_orders": 0,
    "timestamp": "2025-05-16T22:18:14.295121"
  },
  "inventory_service": {
    "average_response_time": 0.08495435228364316,
    "requests_served": 64,
    "total_items": 60,
    "unique_items": 3,
    "timestamp": "2025-05-16T22:18:14.295121"
  },
  "notification_service": {
    "average_response_time": 0.12150771959470597,
    "requests_served": 34,
    "total_notifications": 0,
    "timestamp": "2025-05-16T22:18:14.295121"
  }
}