{
  "user_service": {
    "average_response_time": 0.19682999155444222,
    "requests_served": 12,
    "total_users": 3,
    "timestamp": "2025-05-11T04:00:55.491416"
  },
  "order_service": {
    "average_response_time": 0.3604154240783922,
    "requests_served": 38,
    "total_orders": 2,
    "timestamp": "2025-05-11T04:00:55.491416"
  },
  "inventory_service": {
    "average_response_time": 0.24878519129683696,
    "requests_served": 78,
    "total_items": 60,
    "unique_items": 3,
    "timestamp": "2025-05-11T04:00:55.491416"
  },
  "notification_service": {
    "average_response_time": 0.13243317817141514,
    "requests_served": 32,
    "total_notifications": 0,
    "timestamp": "2025-05-11T04:00:55.491416"
  }
}