{
  "user_service": {
    "average_response_time": 0.47543331100725983,
    "requests_served": 61,
    "total_users": 3,
    "timestamp": "2025-05-12T03:00:13.793222"
  },
  "order_service": {
    "average_response_time": 0.30276887567299576,
    "requests_served": 48,
    "total_orders": 2,
    "timestamp": "2025-05-12T03:00:13.793222"
  },
  "inventory_service": {
    "average_response_time": 0.17906048625859622,
    "requests_served": 42,
    "total_items": 60,
    "unique_items": 3,
    "timestamp": "2025-05-12T03:00:13.793222"
  },
  "notification_service": {
    "average_response_time": 0.15354699063337793,
    "requests_served": 30,
    "total_notifications": 0,
    "timestamp": "2025-05-12T03:00:13.793222"
  }
}