{
  "user_service": {
    "average_response_time": 0.24315791273881526,
    "requests_served": 21,
    "total_users": 3,
    "timestamp": "2025-05-09T13:27:14.430522"
  },
  "order_service": {
    "average_response_time": 0.35399067940942275,
    "requests_served": 45,
    "total_orders": 2,
    "timestamp": "2025-05-09T13:27:14.430522"
  },
  "inventory_service": {
    "average_response_time": 0.1536031093521783,
    "requests_served": 30,
    "total_items": 60,
    "unique_items": 3,
    "timestamp": "2025-05-09T13:27:14.430522"
  },
  "notification_service": {
    "average_response_time": 0.15406024368554272,
    "requests_served": 6,
    "total_notifications": 0,
    "timestamp": "2025-05-09T13:27:14.430522"
  }
}