{
  "user_service": {
    "average_response_time": 0.3251396536412847,
    "requests_served": 26,
    "total_users": 3,
    "timestamp": "2025-05-12T02:27:42.954926"
  },
  "order_service": {
    "average_response_time": 0.24965427560762926,
    "requests_served": 33,
    "total_orders": 2,
    "timestamp": "2025-05-12T02:27:42.954926"
  },
  "inventory_service": {
    "average_response_time": 0.16678085757122135,
    "requests_served": 70,
    "total_items": 60,
    "unique_items": 3,
    "timestamp": "2025-05-12T02:27:42.954926"
  },
  "notification_service": {
    "average_response_time": 0.12030675484668163,
    "requests_served": 23,
    "total_notifications": 0,
    "timestamp": "2025-05-12T02:27:42.954926"
  }
}