{
  "user_service": {
    "average_response_time": 0.16441583341720956,
    "requests_served": 36,
    "total_users": 3,
    "timestamp": "2025-05-17T22:42:48.851826"
  },
  "order_service": {
    "average_response_time": 0.18233455243204663,
    "cpu_percent": 0.0,
    "memory_mb": 1048.48046875,
    "total_orders": 0,
    "timestamp": "2025-05-17T22:42:48.851826"
  },
  "inventory_service": {
    "average_response_time": 0.06403239918352528,
    "requests_served": 51,
    "total_items": 60,
    "unique_items": 3,
    "timestamp": "2025-05-17T22:42:48.851826"
  },
  "notification_service": {
    "average_response_time": 0.11948934071569677,
    "requests_served": 27,
    "total_notifications": 0,
    "timestamp": "2025-05-17T22:42:48.851826"
  }
}