{
  "user_service": {
    "average_response_time": 0.3272559935782091,
    "requests_served": 61,
    "total_users": 3,
    "timestamp": "2025-05-16T16:35:40.611254"
  },
  "order_service": {
    "average_response_time": 0.19800516217695327,
    "cpu_percent": 0.0,
    "memory_mb": 1037.359375,
    "total_orders": 0,
    "timestamp": "2025-05-16T16:35:40.611254"
  },
  "inventory_service": {
    "average_response_time": 0.2975772420426175,
    "requests_served": 29,
    "total_items": 60,
    "unique_items": 3,
    "timestamp": "2025-05-16T16:35:40.611254"
  },
  "notification_service": {
    "average_response_time": 0.18742315078228378,
    "requests_served": 17,
    "total_notifications": 0,
    "timestamp": "2025-05-16T16:35:40.611254"
  }
}