{
  "user_service": {
    "average_response_time": 0.3160460497148705,
    "requests_served": 65,
    "total_users": 3,
    "timestamp": "2025-05-10T00:09:12.469496"
  },
  "order_service": {
    "average_response_time": 0.47276788857439966,
    "requests_served": 45,
    "total_orders": 2,
    "timestamp": "2025-05-10T00:09:12.469496"
  },
  "inventory_service": {
    "average_response_time": 0.23516351238049982,
    "requests_served": 32,
    "total_items": 60,
    "unique_items": 3,
    "timestamp": "2025-05-10T00:09:12.469496"
  },
  "notification_service": {
    "average_response_time": 0.07066803873950102,
    "requests_served": 34,
    "total_notifications": 0,
    "timestamp": "2025-05-10T00:09:12.469496"
  }
}